{
"type": "FeatureCollection",
                                                                                
"features": [
{ "type": "Feature", "properties": { }, "geometry": { "type": "Polygon", "coordinates": [ [ [ 150.54, -31.04, 0.0 ], [ 150.5635, -31.04, 0.0 ], [ 150.5635, -31.018, 0.0 ], [ 150.54, -31.018, 0.0 ], [ 150.54, -31.04, 0.0 ] ] ] } },
{ "type": "Feature", "properties": { }, "geometry": { "type": "Polygon", "coordinates": [ [ [ 150.5635, -31.04, 0.0 ], [ 150.587, -31.04, 0.0 ], [ 150.587, -31.018, 0.0 ], [ 150.5635, -31.018, 0.0 ], [ 150.5635, -31.04, 0.0 ] ] ] } },
{ "type": "Feature", "properties": { }, "geometry": { "type": "Polygon", "coordinates": [ [ [ 150.587, -31.04, 0.0 ], [ 150.6105, -31.04, 0.0 ], [ 150.6105, -31.018, 0.0 ], [ 150.587, -31.018, 0.0 ], [ 150.587, -31.04, 0.0 ] ] ] } },
{ "type": "Feature", "properties": { }, "geometry": { "type": "Polygon", "coordinates": [ [ [ 150.6105, -31.04, 0.0 ], [ 150.634, -31.04, 0.0 ], [ 150.634, -31.018, 0.0 ], [ 150.6105, -31.018, 0.0 ], [ 150.6105, -31.04, 0.0 ] ] ] } },
{ "type": "Feature", "properties": { }, "geometry": { "type": "Polygon", "coordinates": [ [ [ 150.634, -31.04, 0.0 ], [ 150.6575, -31.04, 0.0 ], [ 150.6575, -31.018, 0.0 ], [ 150.634, -31.018, 0.0 ], [ 150.634, -31.04, 0.0 ] ] ] } },
{ "type": "Feature", "properties": { }, "geometry": { "type": "Polygon", "coordinates": [ [ [ 150.6575, -31.04, 0.0 ], [ 150.681, -31.04, 0.0 ], [ 150.681, -31.018, 0.0 ], [ 150.6575, -31.018, 0.0 ], [ 150.6575, -31.04, 0.0 ] ] ] } },
{ "type": "Feature", "properties": { }, "geometry": { "type": "Polygon", "coordinates": [ [ [ 150.681, -31.04, 0.0 ], [ 150.7045, -31.04, 0.0 ], [ 150.7045, -31.018, 0.0 ], [ 150.681, -31.018, 0.0 ], [ 150.681, -31.04, 0.0 ] ] ] } },
{ "type": "Feature", "properties": { }, "geometry": { "type": "Polygon", "coordinates": [ [ [ 150.7045, -31.04, 0.0 ], [ 150.728, -31.04, 0.0 ], [ 150.728, -31.018, 0.0 ], [ 150.7045, -31.018, 0.0 ], [ 150.7045, -31.04, 0.0 ] ] ] } },
{ "type": "Feature", "properties": { }, "geometry": { "type": "Polygon", "coordinates": [ [ [ 150.728, -31.04, 0.0 ], [ 150.7515, -31.04, 0.0 ], [ 150.7515, -31.018, 0.0 ], [ 150.728, -31.018, 0.0 ], [ 150.728, -31.04, 0.0 ] ] ] } },
{ "type": "Feature", "properties": { }, "geometry": { "type": "Polygon", "coordinates": [ [ [ 150.7515, -31.04, 0.0 ], [ 150.775, -31.04, 0.0 ], [ 150.775, -31.018, 0.0 ], [ 150.7515, -31.018, 0.0 ], [ 150.7515, -31.04, 0.0 ] ] ] } },
{ "type": "Feature", "properties": { }, "geometry": { "type": "Polygon", "coordinates": [ [ [ 150.775, -31.04, 0.0 ], [ 150.7985, -31.04, 0.0 ], [ 150.7985, -31.018, 0.0 ], [ 150.775, -31.018, 0.0 ], [ 150.775, -31.04, 0.0 ] ] ] } },
{ "type": "Feature", "properties": { }, "geometry": { "type": "Polygon", "coordinates": [ [ [ 150.7985, -31.04, 0.0 ], [ 150.822, -31.04, 0.0 ], [ 150.822, -31.018, 0.0 ], [ 150.7985, -31.018, 0.0 ], [ 150.7985, -31.04, 0.0 ] ] ] } },
{ "type": "Feature", "properties": { }, "geometry": { "type": "Polygon", "coordinates": [ [ [ 150.822, -31.04, 0.0 ], [ 150.8455, -31.04, 0.0 ], [ 150.8455, -31.018, 0.0 ], [ 150.822, -31.018, 0.0 ], [ 150.822, -31.04, 0.0 ] ] ] } },
{ "type": "Feature", "properties": { }, "geometry": { "type": "Polygon", "coordinates": [ [ [ 150.8455, -31.04, 0.0 ], [ 150.869, -31.04, 0.0 ], [ 150.869, -31.018, 0.0 ], [ 150.8455, -31.018, 0.0 ], [ 150.8455, -31.04, 0.0 ] ] ] } },
{ "type": "Feature", "properties": { }, "geometry": { "type": "Polygon", "coordinates": [ [ [ 150.869, -31.04, 0.0 ], [ 150.8925, -31.04, 0.0 ], [ 150.8925, -31.018, 0.0 ], [ 150.869, -31.018, 0.0 ], [ 150.869, -31.04, 0.0 ] ] ] } },
{ "type": "Feature", "properties": { }, "geometry": { "type": "Polygon", "coordinates": [ [ [ 150.8925, -31.04, 0.0 ], [ 150.916, -31.04, 0.0 ], [ 150.916, -31.018, 0.0 ], [ 150.8925, -31.018, 0.0 ], [ 150.8925, -31.04, 0.0 ] ] ] } },
{ "type": "Feature", "properties": { }, "geometry": { "type": "Polygon", "coordinates": [ [ [ 150.916, -31.04, 0.0 ], [ 150.9395, -31.04, 0.0 ], [ 150.9395, -31.018, 0.0 ], [ 150.916, -31.018, 0.0 ], [ 150.916, -31.04, 0.0 ] ] ] } },
{ "type": "Feature", "properties": { }, "geometry": { "type": "Polygon", "coordinates": [ [ [ 150.9395, -31.04, 0.0 ], [ 150.963, -31.04, 0.0 ], [ 150.963, -31.018, 0.0 ], [ 150.9395, -31.018, 0.0 ], [ 150.9395, -31.04, 0.0 ] ] ] } },
{ "type": "Feature", "properties": { }, "geometry": { "type": "Polygon", "coordinates": [ [ [ 150.963, -31.04, 0.0 ], [ 150.9865, -31.04, 0.0 ], [ 150.9865, -31.018, 0.0 ], [ 150.963, -31.018, 0.0 ], [ 150.963, -31.04, 0.0 ] ] ] } },
{ "type": "Feature", "properties": { }, "geometry": { "type": "Polygon", "coordinates": [ [ [ 150.9865, -31.04, 0.0 ], [ 151.01, -31.04, 0.0 ], [ 151.01, -31.018, 0.0 ], [ 150.9865, -31.018, 0.0 ], [ 150.9865, -31.04, 0.0 ] ] ] } },
{ "type": "Feature", "properties": { }, "geometry": { "type": "Polygon", "coordinates": [ [ [ 150.54, -31.018, 0.0 ], [ 150.5635, -31.018, 0.0 ], [ 150.5635, -30.996, 0.0 ], [ 150.54, -30.996, 0.0 ], [ 150.54, -31.018, 0.0 ] ] ] } },
{ "type": "Feature", "properties": { }, "geometry": { "type": "Polygon", "coordinates": [ [ [ 150.5635, -31.018, 0.0 ], [ 150.587, -31.018, 0.0 ], [ 150.587, -30.996, 0.0 ], [ 150.5635, -30.996, 0.0 ], [ 150.5635, -31.018, 0.0 ] ] ] } },
{ "type": "Feature", "properties": { }, "geometry": { "type": "Polygon", "coordinates": [ [ [ 150.587, -31.018, 0.0 ], [ 150.6105, -31.018, 0.0 ], [ 150.6105, -30.996, 0.0 ], [ 150.587, -30.996, 0.0 ], [ 150.587, -31.018, 0.0 ] ] ] } },
{ "type": "Feature", "properties": { }, "geometry": { "type": "Polygon", "coordinates": [ [ [ 150.6105, -31.018, 0.0 ], [ 150.634, -31.018, 0.0 ], [ 150.634, -30.996, 0.0 ], [ 150.6105, -30.996, 0.0 ], [ 150.6105, -31.018, 0.0 ] ] ] } },
{ "type": "Feature", "properties": { }, "geometry": { "type": "Polygon", "coordinates": [ [ [ 150.634, -31.018, 0.0 ], [ 150.6575, -31.018, 0.0 ], [ 150.6575, -30.996, 0.0 ], [ 150.634, -30.996, 0.0 ], [ 150.634, -31.018, 0.0 ] ] ] } },
{ "type": "Feature", "properties": { }, "geometry": { "type": "Polygon", "coordinates": [ [ [ 150.6575, -31.018, 0.0 ], [ 150.681, -31.018, 0.0 ], [ 150.681, -30.996, 0.0 ], [ 150.6575, -30.996, 0.0 ], [ 150.6575, -31.018, 0.0 ] ] ] } },
{ "type": "Feature", "properties": { }, "geometry": { "type": "Polygon", "coordinates": [ [ [ 150.681, -31.018, 0.0 ], [ 150.7045, -31.018, 0.0 ], [ 150.7045, -30.996, 0.0 ], [ 150.681, -30.996, 0.0 ], [ 150.681, -31.018, 0.0 ] ] ] } },
{ "type": "Feature", "properties": { }, "geometry": { "type": "Polygon", "coordinates": [ [ [ 150.7045, -31.018, 0.0 ], [ 150.728, -31.018, 0.0 ], [ 150.728, -30.996, 0.0 ], [ 150.7045, -30.996, 0.0 ], [ 150.7045, -31.018, 0.0 ] ] ] } },
{ "type": "Feature", "properties": { }, "geometry": { "type": "Polygon", "coordinates": [ [ [ 150.728, -31.018, 0.0 ], [ 150.7515, -31.018, 0.0 ], [ 150.7515, -30.996, 0.0 ], [ 150.728, -30.996, 0.0 ], [ 150.728, -31.018, 0.0 ] ] ] } },
{ "type": "Feature", "properties": { }, "geometry": { "type": "Polygon", "coordinates": [ [ [ 150.7515, -31.018, 0.0 ], [ 150.775, -31.018, 0.0 ], [ 150.775, -30.996, 0.0 ], [ 150.7515, -30.996, 0.0 ], [ 150.7515, -31.018, 0.0 ] ] ] } },
{ "type": "Feature", "properties": { }, "geometry": { "type": "Polygon", "coordinates": [ [ [ 150.775, -31.018, 0.0 ], [ 150.7985, -31.018, 0.0 ], [ 150.7985, -30.996, 0.0 ], [ 150.775, -30.996, 0.0 ], [ 150.775, -31.018, 0.0 ] ] ] } },
{ "type": "Feature", "properties": { }, "geometry": { "type": "Polygon", "coordinates": [ [ [ 150.7985, -31.018, 0.0 ], [ 150.822, -31.018, 0.0 ], [ 150.822, -30.996, 0.0 ], [ 150.7985, -30.996, 0.0 ], [ 150.7985, -31.018, 0.0 ] ] ] } },
{ "type": "Feature", "properties": { }, "geometry": { "type": "Polygon", "coordinates": [ [ [ 150.822, -31.018, 0.0 ], [ 150.8455, -31.018, 0.0 ], [ 150.8455, -30.996, 0.0 ], [ 150.822, -30.996, 0.0 ], [ 150.822, -31.018, 0.0 ] ] ] } },
{ "type": "Feature", "properties": { }, "geometry": { "type": "Polygon", "coordinates": [ [ [ 150.8455, -31.018, 0.0 ], [ 150.869, -31.018, 0.0 ], [ 150.869, -30.996, 0.0 ], [ 150.8455, -30.996, 0.0 ], [ 150.8455, -31.018, 0.0 ] ] ] } },
{ "type": "Feature", "properties": { }, "geometry": { "type": "Polygon", "coordinates": [ [ [ 150.869, -31.018, 0.0 ], [ 150.8925, -31.018, 0.0 ], [ 150.8925, -30.996, 0.0 ], [ 150.869, -30.996, 0.0 ], [ 150.869, -31.018, 0.0 ] ] ] } },
{ "type": "Feature", "properties": { }, "geometry": { "type": "Polygon", "coordinates": [ [ [ 150.8925, -31.018, 0.0 ], [ 150.916, -31.018, 0.0 ], [ 150.916, -30.996, 0.0 ], [ 150.8925, -30.996, 0.0 ], [ 150.8925, -31.018, 0.0 ] ] ] } },
{ "type": "Feature", "properties": { }, "geometry": { "type": "Polygon", "coordinates": [ [ [ 150.916, -31.018, 0.0 ], [ 150.9395, -31.018, 0.0 ], [ 150.9395, -30.996, 0.0 ], [ 150.916, -30.996, 0.0 ], [ 150.916, -31.018, 0.0 ] ] ] } },
{ "type": "Feature", "properties": { }, "geometry": { "type": "Polygon", "coordinates": [ [ [ 150.9395, -31.018, 0.0 ], [ 150.963, -31.018, 0.0 ], [ 150.963, -30.996, 0.0 ], [ 150.9395, -30.996, 0.0 ], [ 150.9395, -31.018, 0.0 ] ] ] } },
{ "type": "Feature", "properties": { }, "geometry": { "type": "Polygon", "coordinates": [ [ [ 150.963, -31.018, 0.0 ], [ 150.9865, -31.018, 0.0 ], [ 150.9865, -30.996, 0.0 ], [ 150.963, -30.996, 0.0 ], [ 150.963, -31.018, 0.0 ] ] ] } },
{ "type": "Feature", "properties": { }, "geometry": { "type": "Polygon", "coordinates": [ [ [ 150.9865, -31.018, 0.0 ], [ 151.01, -31.018, 0.0 ], [ 151.01, -30.996, 0.0 ], [ 150.9865, -30.996, 0.0 ], [ 150.9865, -31.018, 0.0 ] ] ] } },
{ "type": "Feature", "properties": { }, "geometry": { "type": "Polygon", "coordinates": [ [ [ 150.54, -30.996, 0.0 ], [ 150.5635, -30.996, 0.0 ], [ 150.5635, -30.974, 0.0 ], [ 150.54, -30.974, 0.0 ], [ 150.54, -30.996, 0.0 ] ] ] } },
{ "type": "Feature", "properties": { }, "geometry": { "type": "Polygon", "coordinates": [ [ [ 150.5635, -30.996, 0.0 ], [ 150.587, -30.996, 0.0 ], [ 150.587, -30.974, 0.0 ], [ 150.5635, -30.974, 0.0 ], [ 150.5635, -30.996, 0.0 ] ] ] } },
{ "type": "Feature", "properties": { }, "geometry": { "type": "Polygon", "coordinates": [ [ [ 150.587, -30.996, 0.0 ], [ 150.6105, -30.996, 0.0 ], [ 150.6105, -30.974, 0.0 ], [ 150.587, -30.974, 0.0 ], [ 150.587, -30.996, 0.0 ] ] ] } },
{ "type": "Feature", "properties": { }, "geometry": { "type": "Polygon", "coordinates": [ [ [ 150.6105, -30.996, 0.0 ], [ 150.634, -30.996, 0.0 ], [ 150.634, -30.974, 0.0 ], [ 150.6105, -30.974, 0.0 ], [ 150.6105, -30.996, 0.0 ] ] ] } },
{ "type": "Feature", "properties": { }, "geometry": { "type": "Polygon", "coordinates": [ [ [ 150.634, -30.996, 0.0 ], [ 150.6575, -30.996, 0.0 ], [ 150.6575, -30.974, 0.0 ], [ 150.634, -30.974, 0.0 ], [ 150.634, -30.996, 0.0 ] ] ] } },
{ "type": "Feature", "properties": { }, "geometry": { "type": "Polygon", "coordinates": [ [ [ 150.6575, -30.996, 0.0 ], [ 150.681, -30.996, 0.0 ], [ 150.681, -30.974, 0.0 ], [ 150.6575, -30.974, 0.0 ], [ 150.6575, -30.996, 0.0 ] ] ] } },
{ "type": "Feature", "properties": { }, "geometry": { "type": "Polygon", "coordinates": [ [ [ 150.681, -30.996, 0.0 ], [ 150.7045, -30.996, 0.0 ], [ 150.7045, -30.974, 0.0 ], [ 150.681, -30.974, 0.0 ], [ 150.681, -30.996, 0.0 ] ] ] } },
{ "type": "Feature", "properties": { }, "geometry": { "type": "Polygon", "coordinates": [ [ [ 150.7045, -30.996, 0.0 ], [ 150.728, -30.996, 0.0 ], [ 150.728, -30.974, 0.0 ], [ 150.7045, -30.974, 0.0 ], [ 150.7045, -30.996, 0.0 ] ] ] } },
{ "type": "Feature", "properties": { }, "geometry": { "type": "Polygon", "coordinates": [ [ [ 150.728, -30.996, 0.0 ], [ 150.7515, -30.996, 0.0 ], [ 150.7515, -30.974, 0.0 ], [ 150.728, -30.974, 0.0 ], [ 150.728, -30.996, 0.0 ] ] ] } },
{ "type": "Feature", "properties": { }, "geometry": { "type": "Polygon", "coordinates": [ [ [ 150.7515, -30.996, 0.0 ], [ 150.775, -30.996, 0.0 ], [ 150.775, -30.974, 0.0 ], [ 150.7515, -30.974, 0.0 ], [ 150.7515, -30.996, 0.0 ] ] ] } },
{ "type": "Feature", "properties": { }, "geometry": { "type": "Polygon", "coordinates": [ [ [ 150.775, -30.996, 0.0 ], [ 150.7985, -30.996, 0.0 ], [ 150.7985, -30.974, 0.0 ], [ 150.775, -30.974, 0.0 ], [ 150.775, -30.996, 0.0 ] ] ] } },
{ "type": "Feature", "properties": { }, "geometry": { "type": "Polygon", "coordinates": [ [ [ 150.7985, -30.996, 0.0 ], [ 150.822, -30.996, 0.0 ], [ 150.822, -30.974, 0.0 ], [ 150.7985, -30.974, 0.0 ], [ 150.7985, -30.996, 0.0 ] ] ] } },
{ "type": "Feature", "properties": { }, "geometry": { "type": "Polygon", "coordinates": [ [ [ 150.822, -30.996, 0.0 ], [ 150.8455, -30.996, 0.0 ], [ 150.8455, -30.974, 0.0 ], [ 150.822, -30.974, 0.0 ], [ 150.822, -30.996, 0.0 ] ] ] } },
{ "type": "Feature", "properties": { }, "geometry": { "type": "Polygon", "coordinates": [ [ [ 150.8455, -30.996, 0.0 ], [ 150.869, -30.996, 0.0 ], [ 150.869, -30.974, 0.0 ], [ 150.8455, -30.974, 0.0 ], [ 150.8455, -30.996, 0.0 ] ] ] } },
{ "type": "Feature", "properties": { }, "geometry": { "type": "Polygon", "coordinates": [ [ [ 150.869, -30.996, 0.0 ], [ 150.8925, -30.996, 0.0 ], [ 150.8925, -30.974, 0.0 ], [ 150.869, -30.974, 0.0 ], [ 150.869, -30.996, 0.0 ] ] ] } },
{ "type": "Feature", "properties": { }, "geometry": { "type": "Polygon", "coordinates": [ [ [ 150.8925, -30.996, 0.0 ], [ 150.916, -30.996, 0.0 ], [ 150.916, -30.974, 0.0 ], [ 150.8925, -30.974, 0.0 ], [ 150.8925, -30.996, 0.0 ] ] ] } },
{ "type": "Feature", "properties": { }, "geometry": { "type": "Polygon", "coordinates": [ [ [ 150.916, -30.996, 0.0 ], [ 150.9395, -30.996, 0.0 ], [ 150.9395, -30.974, 0.0 ], [ 150.916, -30.974, 0.0 ], [ 150.916, -30.996, 0.0 ] ] ] } },
{ "type": "Feature", "properties": { }, "geometry": { "type": "Polygon", "coordinates": [ [ [ 150.9395, -30.996, 0.0 ], [ 150.963, -30.996, 0.0 ], [ 150.963, -30.974, 0.0 ], [ 150.9395, -30.974, 0.0 ], [ 150.9395, -30.996, 0.0 ] ] ] } },
{ "type": "Feature", "properties": { }, "geometry": { "type": "Polygon", "coordinates": [ [ [ 150.963, -30.996, 0.0 ], [ 150.9865, -30.996, 0.0 ], [ 150.9865, -30.974, 0.0 ], [ 150.963, -30.974, 0.0 ], [ 150.963, -30.996, 0.0 ] ] ] } },
{ "type": "Feature", "properties": { }, "geometry": { "type": "Polygon", "coordinates": [ [ [ 150.9865, -30.996, 0.0 ], [ 151.01, -30.996, 0.0 ], [ 151.01, -30.974, 0.0 ], [ 150.9865, -30.974, 0.0 ], [ 150.9865, -30.996, 0.0 ] ] ] } },
{ "type": "Feature", "properties": { }, "geometry": { "type": "Polygon", "coordinates": [ [ [ 150.54, -30.974, 0.0 ], [ 150.5635, -30.974, 0.0 ], [ 150.5635, -30.952, 0.0 ], [ 150.54, -30.952, 0.0 ], [ 150.54, -30.974, 0.0 ] ] ] } },
{ "type": "Feature", "properties": { }, "geometry": { "type": "Polygon", "coordinates": [ [ [ 150.5635, -30.974, 0.0 ], [ 150.587, -30.974, 0.0 ], [ 150.587, -30.952, 0.0 ], [ 150.5635, -30.952, 0.0 ], [ 150.5635, -30.974, 0.0 ] ] ] } },
{ "type": "Feature", "properties": { }, "geometry": { "type": "Polygon", "coordinates": [ [ [ 150.587, -30.974, 0.0 ], [ 150.6105, -30.974, 0.0 ], [ 150.6105, -30.952, 0.0 ], [ 150.587, -30.952, 0.0 ], [ 150.587, -30.974, 0.0 ] ] ] } },
{ "type": "Feature", "properties": { }, "geometry": { "type": "Polygon", "coordinates": [ [ [ 150.6105, -30.974, 0.0 ], [ 150.634, -30.974, 0.0 ], [ 150.634, -30.952, 0.0 ], [ 150.6105, -30.952, 0.0 ], [ 150.6105, -30.974, 0.0 ] ] ] } },
{ "type": "Feature", "properties": { }, "geometry": { "type": "Polygon", "coordinates": [ [ [ 150.634, -30.974, 0.0 ], [ 150.6575, -30.974, 0.0 ], [ 150.6575, -30.952, 0.0 ], [ 150.634, -30.952, 0.0 ], [ 150.634, -30.974, 0.0 ] ] ] } },
{ "type": "Feature", "properties": { }, "geometry": { "type": "Polygon", "coordinates": [ [ [ 150.6575, -30.974, 0.0 ], [ 150.681, -30.974, 0.0 ], [ 150.681, -30.952, 0.0 ], [ 150.6575, -30.952, 0.0 ], [ 150.6575, -30.974, 0.0 ] ] ] } },
{ "type": "Feature", "properties": { }, "geometry": { "type": "Polygon", "coordinates": [ [ [ 150.681, -30.974, 0.0 ], [ 150.7045, -30.974, 0.0 ], [ 150.7045, -30.952, 0.0 ], [ 150.681, -30.952, 0.0 ], [ 150.681, -30.974, 0.0 ] ] ] } },
{ "type": "Feature", "properties": { }, "geometry": { "type": "Polygon", "coordinates": [ [ [ 150.7045, -30.974, 0.0 ], [ 150.728, -30.974, 0.0 ], [ 150.728, -30.952, 0.0 ], [ 150.7045, -30.952, 0.0 ], [ 150.7045, -30.974, 0.0 ] ] ] } },
{ "type": "Feature", "properties": { }, "geometry": { "type": "Polygon", "coordinates": [ [ [ 150.728, -30.974, 0.0 ], [ 150.7515, -30.974, 0.0 ], [ 150.7515, -30.952, 0.0 ], [ 150.728, -30.952, 0.0 ], [ 150.728, -30.974, 0.0 ] ] ] } },
{ "type": "Feature", "properties": { }, "geometry": { "type": "Polygon", "coordinates": [ [ [ 150.7515, -30.974, 0.0 ], [ 150.775, -30.974, 0.0 ], [ 150.775, -30.952, 0.0 ], [ 150.7515, -30.952, 0.0 ], [ 150.7515, -30.974, 0.0 ] ] ] } },
{ "type": "Feature", "properties": { }, "geometry": { "type": "Polygon", "coordinates": [ [ [ 150.775, -30.974, 0.0 ], [ 150.7985, -30.974, 0.0 ], [ 150.7985, -30.952, 0.0 ], [ 150.775, -30.952, 0.0 ], [ 150.775, -30.974, 0.0 ] ] ] } },
{ "type": "Feature", "properties": { }, "geometry": { "type": "Polygon", "coordinates": [ [ [ 150.7985, -30.974, 0.0 ], [ 150.822, -30.974, 0.0 ], [ 150.822, -30.952, 0.0 ], [ 150.7985, -30.952, 0.0 ], [ 150.7985, -30.974, 0.0 ] ] ] } },
{ "type": "Feature", "properties": { }, "geometry": { "type": "Polygon", "coordinates": [ [ [ 150.822, -30.974, 0.0 ], [ 150.8455, -30.974, 0.0 ], [ 150.8455, -30.952, 0.0 ], [ 150.822, -30.952, 0.0 ], [ 150.822, -30.974, 0.0 ] ] ] } },
{ "type": "Feature", "properties": { }, "geometry": { "type": "Polygon", "coordinates": [ [ [ 150.8455, -30.974, 0.0 ], [ 150.869, -30.974, 0.0 ], [ 150.869, -30.952, 0.0 ], [ 150.8455, -30.952, 0.0 ], [ 150.8455, -30.974, 0.0 ] ] ] } },
{ "type": "Feature", "properties": { }, "geometry": { "type": "Polygon", "coordinates": [ [ [ 150.869, -30.974, 0.0 ], [ 150.8925, -30.974, 0.0 ], [ 150.8925, -30.952, 0.0 ], [ 150.869, -30.952, 0.0 ], [ 150.869, -30.974, 0.0 ] ] ] } },
{ "type": "Feature", "properties": { }, "geometry": { "type": "Polygon", "coordinates": [ [ [ 150.8925, -30.974, 0.0 ], [ 150.916, -30.974, 0.0 ], [ 150.916, -30.952, 0.0 ], [ 150.8925, -30.952, 0.0 ], [ 150.8925, -30.974, 0.0 ] ] ] } },
{ "type": "Feature", "properties": { }, "geometry": { "type": "Polygon", "coordinates": [ [ [ 150.916, -30.974, 0.0 ], [ 150.9395, -30.974, 0.0 ], [ 150.9395, -30.952, 0.0 ], [ 150.916, -30.952, 0.0 ], [ 150.916, -30.974, 0.0 ] ] ] } },
{ "type": "Feature", "properties": { }, "geometry": { "type": "Polygon", "coordinates": [ [ [ 150.9395, -30.974, 0.0 ], [ 150.963, -30.974, 0.0 ], [ 150.963, -30.952, 0.0 ], [ 150.9395, -30.952, 0.0 ], [ 150.9395, -30.974, 0.0 ] ] ] } },
{ "type": "Feature", "properties": { }, "geometry": { "type": "Polygon", "coordinates": [ [ [ 150.963, -30.974, 0.0 ], [ 150.9865, -30.974, 0.0 ], [ 150.9865, -30.952, 0.0 ], [ 150.963, -30.952, 0.0 ], [ 150.963, -30.974, 0.0 ] ] ] } },
{ "type": "Feature", "properties": { }, "geometry": { "type": "Polygon", "coordinates": [ [ [ 150.9865, -30.974, 0.0 ], [ 151.01, -30.974, 0.0 ], [ 151.01, -30.952, 0.0 ], [ 150.9865, -30.952, 0.0 ], [ 150.9865, -30.974, 0.0 ] ] ] } },
{ "type": "Feature", "properties": { }, "geometry": { "type": "Polygon", "coordinates": [ [ [ 150.54, -30.952, 0.0 ], [ 150.5635, -30.952, 0.0 ], [ 150.5635, -30.93, 0.0 ], [ 150.54, -30.93, 0.0 ], [ 150.54, -30.952, 0.0 ] ] ] } },
{ "type": "Feature", "properties": { }, "geometry": { "type": "Polygon", "coordinates": [ [ [ 150.5635, -30.952, 0.0 ], [ 150.587, -30.952, 0.0 ], [ 150.587, -30.93, 0.0 ], [ 150.5635, -30.93, 0.0 ], [ 150.5635, -30.952, 0.0 ] ] ] } },
{ "type": "Feature", "properties": { }, "geometry": { "type": "Polygon", "coordinates": [ [ [ 150.587, -30.952, 0.0 ], [ 150.6105, -30.952, 0.0 ], [ 150.6105, -30.93, 0.0 ], [ 150.587, -30.93, 0.0 ], [ 150.587, -30.952, 0.0 ] ] ] } },
{ "type": "Feature", "properties": { }, "geometry": { "type": "Polygon", "coordinates": [ [ [ 150.6105, -30.952, 0.0 ], [ 150.634, -30.952, 0.0 ], [ 150.634, -30.93, 0.0 ], [ 150.6105, -30.93, 0.0 ], [ 150.6105, -30.952, 0.0 ] ] ] } },
{ "type": "Feature", "properties": { }, "geometry": { "type": "Polygon", "coordinates": [ [ [ 150.634, -30.952, 0.0 ], [ 150.6575, -30.952, 0.0 ], [ 150.6575, -30.93, 0.0 ], [ 150.634, -30.93, 0.0 ], [ 150.634, -30.952, 0.0 ] ] ] } },
{ "type": "Feature", "properties": { }, "geometry": { "type": "Polygon", "coordinates": [ [ [ 150.6575, -30.952, 0.0 ], [ 150.681, -30.952, 0.0 ], [ 150.681, -30.93, 0.0 ], [ 150.6575, -30.93, 0.0 ], [ 150.6575, -30.952, 0.0 ] ] ] } },
{ "type": "Feature", "properties": { }, "geometry": { "type": "Polygon", "coordinates": [ [ [ 150.681, -30.952, 0.0 ], [ 150.7045, -30.952, 0.0 ], [ 150.7045, -30.93, 0.0 ], [ 150.681, -30.93, 0.0 ], [ 150.681, -30.952, 0.0 ] ] ] } },
{ "type": "Feature", "properties": { }, "geometry": { "type": "Polygon", "coordinates": [ [ [ 150.7045, -30.952, 0.0 ], [ 150.728, -30.952, 0.0 ], [ 150.728, -30.93, 0.0 ], [ 150.7045, -30.93, 0.0 ], [ 150.7045, -30.952, 0.0 ] ] ] } },
{ "type": "Feature", "properties": { }, "geometry": { "type": "Polygon", "coordinates": [ [ [ 150.728, -30.952, 0.0 ], [ 150.7515, -30.952, 0.0 ], [ 150.7515, -30.93, 0.0 ], [ 150.728, -30.93, 0.0 ], [ 150.728, -30.952, 0.0 ] ] ] } },
{ "type": "Feature", "properties": { }, "geometry": { "type": "Polygon", "coordinates": [ [ [ 150.7515, -30.952, 0.0 ], [ 150.775, -30.952, 0.0 ], [ 150.775, -30.93, 0.0 ], [ 150.7515, -30.93, 0.0 ], [ 150.7515, -30.952, 0.0 ] ] ] } },
{ "type": "Feature", "properties": { }, "geometry": { "type": "Polygon", "coordinates": [ [ [ 150.775, -30.952, 0.0 ], [ 150.7985, -30.952, 0.0 ], [ 150.7985, -30.93, 0.0 ], [ 150.775, -30.93, 0.0 ], [ 150.775, -30.952, 0.0 ] ] ] } },
{ "type": "Feature", "properties": { }, "geometry": { "type": "Polygon", "coordinates": [ [ [ 150.7985, -30.952, 0.0 ], [ 150.822, -30.952, 0.0 ], [ 150.822, -30.93, 0.0 ], [ 150.7985, -30.93, 0.0 ], [ 150.7985, -30.952, 0.0 ] ] ] } },
{ "type": "Feature", "properties": { }, "geometry": { "type": "Polygon", "coordinates": [ [ [ 150.822, -30.952, 0.0 ], [ 150.8455, -30.952, 0.0 ], [ 150.8455, -30.93, 0.0 ], [ 150.822, -30.93, 0.0 ], [ 150.822, -30.952, 0.0 ] ] ] } },
{ "type": "Feature", "properties": { }, "geometry": { "type": "Polygon", "coordinates": [ [ [ 150.8455, -30.952, 0.0 ], [ 150.869, -30.952, 0.0 ], [ 150.869, -30.93, 0.0 ], [ 150.8455, -30.93, 0.0 ], [ 150.8455, -30.952, 0.0 ] ] ] } },
{ "type": "Feature", "properties": { }, "geometry": { "type": "Polygon", "coordinates": [ [ [ 150.869, -30.952, 0.0 ], [ 150.8925, -30.952, 0.0 ], [ 150.8925, -30.93, 0.0 ], [ 150.869, -30.93, 0.0 ], [ 150.869, -30.952, 0.0 ] ] ] } },
{ "type": "Feature", "properties": { }, "geometry": { "type": "Polygon", "coordinates": [ [ [ 150.8925, -30.952, 0.0 ], [ 150.916, -30.952, 0.0 ], [ 150.916, -30.93, 0.0 ], [ 150.8925, -30.93, 0.0 ], [ 150.8925, -30.952, 0.0 ] ] ] } },
{ "type": "Feature", "properties": { }, "geometry": { "type": "Polygon", "coordinates": [ [ [ 150.916, -30.952, 0.0 ], [ 150.9395, -30.952, 0.0 ], [ 150.9395, -30.93, 0.0 ], [ 150.916, -30.93, 0.0 ], [ 150.916, -30.952, 0.0 ] ] ] } },
{ "type": "Feature", "properties": { }, "geometry": { "type": "Polygon", "coordinates": [ [ [ 150.9395, -30.952, 0.0 ], [ 150.963, -30.952, 0.0 ], [ 150.963, -30.93, 0.0 ], [ 150.9395, -30.93, 0.0 ], [ 150.9395, -30.952, 0.0 ] ] ] } },
{ "type": "Feature", "properties": { }, "geometry": { "type": "Polygon", "coordinates": [ [ [ 150.963, -30.952, 0.0 ], [ 150.9865, -30.952, 0.0 ], [ 150.9865, -30.93, 0.0 ], [ 150.963, -30.93, 0.0 ], [ 150.963, -30.952, 0.0 ] ] ] } },
{ "type": "Feature", "properties": { }, "geometry": { "type": "Polygon", "coordinates": [ [ [ 150.9865, -30.952, 0.0 ], [ 151.01, -30.952, 0.0 ], [ 151.01, -30.93, 0.0 ], [ 150.9865, -30.93, 0.0 ], [ 150.9865, -30.952, 0.0 ] ] ] } },
{ "type": "Feature", "properties": { }, "geometry": { "type": "Polygon", "coordinates": [ [ [ 150.54, -30.93, 0.0 ], [ 150.5635, -30.93, 0.0 ], [ 150.5635, -30.908, 0.0 ], [ 150.54, -30.908, 0.0 ], [ 150.54, -30.93, 0.0 ] ] ] } },
{ "type": "Feature", "properties": { }, "geometry": { "type": "Polygon", "coordinates": [ [ [ 150.5635, -30.93, 0.0 ], [ 150.587, -30.93, 0.0 ], [ 150.587, -30.908, 0.0 ], [ 150.5635, -30.908, 0.0 ], [ 150.5635, -30.93, 0.0 ] ] ] } },
{ "type": "Feature", "properties": { }, "geometry": { "type": "Polygon", "coordinates": [ [ [ 150.587, -30.93, 0.0 ], [ 150.6105, -30.93, 0.0 ], [ 150.6105, -30.908, 0.0 ], [ 150.587, -30.908, 0.0 ], [ 150.587, -30.93, 0.0 ] ] ] } },
{ "type": "Feature", "properties": { }, "geometry": { "type": "Polygon", "coordinates": [ [ [ 150.6105, -30.93, 0.0 ], [ 150.634, -30.93, 0.0 ], [ 150.634, -30.908, 0.0 ], [ 150.6105, -30.908, 0.0 ], [ 150.6105, -30.93, 0.0 ] ] ] } },
{ "type": "Feature", "properties": { }, "geometry": { "type": "Polygon", "coordinates": [ [ [ 150.634, -30.93, 0.0 ], [ 150.6575, -30.93, 0.0 ], [ 150.6575, -30.908, 0.0 ], [ 150.634, -30.908, 0.0 ], [ 150.634, -30.93, 0.0 ] ] ] } },
{ "type": "Feature", "properties": { }, "geometry": { "type": "Polygon", "coordinates": [ [ [ 150.6575, -30.93, 0.0 ], [ 150.681, -30.93, 0.0 ], [ 150.681, -30.908, 0.0 ], [ 150.6575, -30.908, 0.0 ], [ 150.6575, -30.93, 0.0 ] ] ] } },
{ "type": "Feature", "properties": { }, "geometry": { "type": "Polygon", "coordinates": [ [ [ 150.681, -30.93, 0.0 ], [ 150.7045, -30.93, 0.0 ], [ 150.7045, -30.908, 0.0 ], [ 150.681, -30.908, 0.0 ], [ 150.681, -30.93, 0.0 ] ] ] } },
{ "type": "Feature", "properties": { }, "geometry": { "type": "Polygon", "coordinates": [ [ [ 150.7045, -30.93, 0.0 ], [ 150.728, -30.93, 0.0 ], [ 150.728, -30.908, 0.0 ], [ 150.7045, -30.908, 0.0 ], [ 150.7045, -30.93, 0.0 ] ] ] } },
{ "type": "Feature", "properties": { }, "geometry": { "type": "Polygon", "coordinates": [ [ [ 150.728, -30.93, 0.0 ], [ 150.7515, -30.93, 0.0 ], [ 150.7515, -30.908, 0.0 ], [ 150.728, -30.908, 0.0 ], [ 150.728, -30.93, 0.0 ] ] ] } },
{ "type": "Feature", "properties": { }, "geometry": { "type": "Polygon", "coordinates": [ [ [ 150.7515, -30.93, 0.0 ], [ 150.775, -30.93, 0.0 ], [ 150.775, -30.908, 0.0 ], [ 150.7515, -30.908, 0.0 ], [ 150.7515, -30.93, 0.0 ] ] ] } },
{ "type": "Feature", "properties": { }, "geometry": { "type": "Polygon", "coordinates": [ [ [ 150.775, -30.93, 0.0 ], [ 150.7985, -30.93, 0.0 ], [ 150.7985, -30.908, 0.0 ], [ 150.775, -30.908, 0.0 ], [ 150.775, -30.93, 0.0 ] ] ] } },
{ "type": "Feature", "properties": { }, "geometry": { "type": "Polygon", "coordinates": [ [ [ 150.7985, -30.93, 0.0 ], [ 150.822, -30.93, 0.0 ], [ 150.822, -30.908, 0.0 ], [ 150.7985, -30.908, 0.0 ], [ 150.7985, -30.93, 0.0 ] ] ] } },
{ "type": "Feature", "properties": { }, "geometry": { "type": "Polygon", "coordinates": [ [ [ 150.822, -30.93, 0.0 ], [ 150.8455, -30.93, 0.0 ], [ 150.8455, -30.908, 0.0 ], [ 150.822, -30.908, 0.0 ], [ 150.822, -30.93, 0.0 ] ] ] } },
{ "type": "Feature", "properties": { }, "geometry": { "type": "Polygon", "coordinates": [ [ [ 150.8455, -30.93, 0.0 ], [ 150.869, -30.93, 0.0 ], [ 150.869, -30.908, 0.0 ], [ 150.8455, -30.908, 0.0 ], [ 150.8455, -30.93, 0.0 ] ] ] } },
{ "type": "Feature", "properties": { }, "geometry": { "type": "Polygon", "coordinates": [ [ [ 150.869, -30.93, 0.0 ], [ 150.8925, -30.93, 0.0 ], [ 150.8925, -30.908, 0.0 ], [ 150.869, -30.908, 0.0 ], [ 150.869, -30.93, 0.0 ] ] ] } },
{ "type": "Feature", "properties": { }, "geometry": { "type": "Polygon", "coordinates": [ [ [ 150.8925, -30.93, 0.0 ], [ 150.916, -30.93, 0.0 ], [ 150.916, -30.908, 0.0 ], [ 150.8925, -30.908, 0.0 ], [ 150.8925, -30.93, 0.0 ] ] ] } },
{ "type": "Feature", "properties": { }, "geometry": { "type": "Polygon", "coordinates": [ [ [ 150.916, -30.93, 0.0 ], [ 150.9395, -30.93, 0.0 ], [ 150.9395, -30.908, 0.0 ], [ 150.916, -30.908, 0.0 ], [ 150.916, -30.93, 0.0 ] ] ] } },
{ "type": "Feature", "properties": { }, "geometry": { "type": "Polygon", "coordinates": [ [ [ 150.9395, -30.93, 0.0 ], [ 150.963, -30.93, 0.0 ], [ 150.963, -30.908, 0.0 ], [ 150.9395, -30.908, 0.0 ], [ 150.9395, -30.93, 0.0 ] ] ] } },
{ "type": "Feature", "properties": { }, "geometry": { "type": "Polygon", "coordinates": [ [ [ 150.963, -30.93, 0.0 ], [ 150.9865, -30.93, 0.0 ], [ 150.9865, -30.908, 0.0 ], [ 150.963, -30.908, 0.0 ], [ 150.963, -30.93, 0.0 ] ] ] } },
{ "type": "Feature", "properties": { }, "geometry": { "type": "Polygon", "coordinates": [ [ [ 150.9865, -30.93, 0.0 ], [ 151.01, -30.93, 0.0 ], [ 151.01, -30.908, 0.0 ], [ 150.9865, -30.908, 0.0 ], [ 150.9865, -30.93, 0.0 ] ] ] } },
{ "type": "Feature", "properties": { }, "geometry": { "type": "Polygon", "coordinates": [ [ [ 150.54, -30.908, 0.0 ], [ 150.5635, -30.908, 0.0 ], [ 150.5635, -30.886, 0.0 ], [ 150.54, -30.886, 0.0 ], [ 150.54, -30.908, 0.0 ] ] ] } },
{ "type": "Feature", "properties": { }, "geometry": { "type": "Polygon", "coordinates": [ [ [ 150.5635, -30.908, 0.0 ], [ 150.587, -30.908, 0.0 ], [ 150.587, -30.886, 0.0 ], [ 150.5635, -30.886, 0.0 ], [ 150.5635, -30.908, 0.0 ] ] ] } },
{ "type": "Feature", "properties": { }, "geometry": { "type": "Polygon", "coordinates": [ [ [ 150.587, -30.908, 0.0 ], [ 150.6105, -30.908, 0.0 ], [ 150.6105, -30.886, 0.0 ], [ 150.587, -30.886, 0.0 ], [ 150.587, -30.908, 0.0 ] ] ] } },
{ "type": "Feature", "properties": { }, "geometry": { "type": "Polygon", "coordinates": [ [ [ 150.6105, -30.908, 0.0 ], [ 150.634, -30.908, 0.0 ], [ 150.634, -30.886, 0.0 ], [ 150.6105, -30.886, 0.0 ], [ 150.6105, -30.908, 0.0 ] ] ] } },
{ "type": "Feature", "properties": { }, "geometry": { "type": "Polygon", "coordinates": [ [ [ 150.634, -30.908, 0.0 ], [ 150.6575, -30.908, 0.0 ], [ 150.6575, -30.886, 0.0 ], [ 150.634, -30.886, 0.0 ], [ 150.634, -30.908, 0.0 ] ] ] } },
{ "type": "Feature", "properties": { }, "geometry": { "type": "Polygon", "coordinates": [ [ [ 150.6575, -30.908, 0.0 ], [ 150.681, -30.908, 0.0 ], [ 150.681, -30.886, 0.0 ], [ 150.6575, -30.886, 0.0 ], [ 150.6575, -30.908, 0.0 ] ] ] } },
{ "type": "Feature", "properties": { }, "geometry": { "type": "Polygon", "coordinates": [ [ [ 150.681, -30.908, 0.0 ], [ 150.7045, -30.908, 0.0 ], [ 150.7045, -30.886, 0.0 ], [ 150.681, -30.886, 0.0 ], [ 150.681, -30.908, 0.0 ] ] ] } },
{ "type": "Feature", "properties": { }, "geometry": { "type": "Polygon", "coordinates": [ [ [ 150.7045, -30.908, 0.0 ], [ 150.728, -30.908, 0.0 ], [ 150.728, -30.886, 0.0 ], [ 150.7045, -30.886, 0.0 ], [ 150.7045, -30.908, 0.0 ] ] ] } },
{ "type": "Feature", "properties": { }, "geometry": { "type": "Polygon", "coordinates": [ [ [ 150.728, -30.908, 0.0 ], [ 150.7515, -30.908, 0.0 ], [ 150.7515, -30.886, 0.0 ], [ 150.728, -30.886, 0.0 ], [ 150.728, -30.908, 0.0 ] ] ] } },
{ "type": "Feature", "properties": { }, "geometry": { "type": "Polygon", "coordinates": [ [ [ 150.7515, -30.908, 0.0 ], [ 150.775, -30.908, 0.0 ], [ 150.775, -30.886, 0.0 ], [ 150.7515, -30.886, 0.0 ], [ 150.7515, -30.908, 0.0 ] ] ] } },
{ "type": "Feature", "properties": { }, "geometry": { "type": "Polygon", "coordinates": [ [ [ 150.775, -30.908, 0.0 ], [ 150.7985, -30.908, 0.0 ], [ 150.7985, -30.886, 0.0 ], [ 150.775, -30.886, 0.0 ], [ 150.775, -30.908, 0.0 ] ] ] } },
{ "type": "Feature", "properties": { }, "geometry": { "type": "Polygon", "coordinates": [ [ [ 150.7985, -30.908, 0.0 ], [ 150.822, -30.908, 0.0 ], [ 150.822, -30.886, 0.0 ], [ 150.7985, -30.886, 0.0 ], [ 150.7985, -30.908, 0.0 ] ] ] } },
{ "type": "Feature", "properties": { }, "geometry": { "type": "Polygon", "coordinates": [ [ [ 150.822, -30.908, 0.0 ], [ 150.8455, -30.908, 0.0 ], [ 150.8455, -30.886, 0.0 ], [ 150.822, -30.886, 0.0 ], [ 150.822, -30.908, 0.0 ] ] ] } },
{ "type": "Feature", "properties": { }, "geometry": { "type": "Polygon", "coordinates": [ [ [ 150.8455, -30.908, 0.0 ], [ 150.869, -30.908, 0.0 ], [ 150.869, -30.886, 0.0 ], [ 150.8455, -30.886, 0.0 ], [ 150.8455, -30.908, 0.0 ] ] ] } },
{ "type": "Feature", "properties": { }, "geometry": { "type": "Polygon", "coordinates": [ [ [ 150.869, -30.908, 0.0 ], [ 150.8925, -30.908, 0.0 ], [ 150.8925, -30.886, 0.0 ], [ 150.869, -30.886, 0.0 ], [ 150.869, -30.908, 0.0 ] ] ] } },
{ "type": "Feature", "properties": { }, "geometry": { "type": "Polygon", "coordinates": [ [ [ 150.8925, -30.908, 0.0 ], [ 150.916, -30.908, 0.0 ], [ 150.916, -30.886, 0.0 ], [ 150.8925, -30.886, 0.0 ], [ 150.8925, -30.908, 0.0 ] ] ] } },
{ "type": "Feature", "properties": { }, "geometry": { "type": "Polygon", "coordinates": [ [ [ 150.916, -30.908, 0.0 ], [ 150.9395, -30.908, 0.0 ], [ 150.9395, -30.886, 0.0 ], [ 150.916, -30.886, 0.0 ], [ 150.916, -30.908, 0.0 ] ] ] } },
{ "type": "Feature", "properties": { }, "geometry": { "type": "Polygon", "coordinates": [ [ [ 150.9395, -30.908, 0.0 ], [ 150.963, -30.908, 0.0 ], [ 150.963, -30.886, 0.0 ], [ 150.9395, -30.886, 0.0 ], [ 150.9395, -30.908, 0.0 ] ] ] } },
{ "type": "Feature", "properties": { }, "geometry": { "type": "Polygon", "coordinates": [ [ [ 150.963, -30.908, 0.0 ], [ 150.9865, -30.908, 0.0 ], [ 150.9865, -30.886, 0.0 ], [ 150.963, -30.886, 0.0 ], [ 150.963, -30.908, 0.0 ] ] ] } },
{ "type": "Feature", "properties": { }, "geometry": { "type": "Polygon", "coordinates": [ [ [ 150.9865, -30.908, 0.0 ], [ 151.01, -30.908, 0.0 ], [ 151.01, -30.886, 0.0 ], [ 150.9865, -30.886, 0.0 ], [ 150.9865, -30.908, 0.0 ] ] ] } },
{ "type": "Feature", "properties": { }, "geometry": { "type": "Polygon", "coordinates": [ [ [ 150.54, -30.886, 0.0 ], [ 150.5635, -30.886, 0.0 ], [ 150.5635, -30.864, 0.0 ], [ 150.54, -30.864, 0.0 ], [ 150.54, -30.886, 0.0 ] ] ] } },
{ "type": "Feature", "properties": { }, "geometry": { "type": "Polygon", "coordinates": [ [ [ 150.5635, -30.886, 0.0 ], [ 150.587, -30.886, 0.0 ], [ 150.587, -30.864, 0.0 ], [ 150.5635, -30.864, 0.0 ], [ 150.5635, -30.886, 0.0 ] ] ] } },
{ "type": "Feature", "properties": { }, "geometry": { "type": "Polygon", "coordinates": [ [ [ 150.587, -30.886, 0.0 ], [ 150.6105, -30.886, 0.0 ], [ 150.6105, -30.864, 0.0 ], [ 150.587, -30.864, 0.0 ], [ 150.587, -30.886, 0.0 ] ] ] } },
{ "type": "Feature", "properties": { }, "geometry": { "type": "Polygon", "coordinates": [ [ [ 150.6105, -30.886, 0.0 ], [ 150.634, -30.886, 0.0 ], [ 150.634, -30.864, 0.0 ], [ 150.6105, -30.864, 0.0 ], [ 150.6105, -30.886, 0.0 ] ] ] } },
{ "type": "Feature", "properties": { }, "geometry": { "type": "Polygon", "coordinates": [ [ [ 150.634, -30.886, 0.0 ], [ 150.6575, -30.886, 0.0 ], [ 150.6575, -30.864, 0.0 ], [ 150.634, -30.864, 0.0 ], [ 150.634, -30.886, 0.0 ] ] ] } },
{ "type": "Feature", "properties": { }, "geometry": { "type": "Polygon", "coordinates": [ [ [ 150.6575, -30.886, 0.0 ], [ 150.681, -30.886, 0.0 ], [ 150.681, -30.864, 0.0 ], [ 150.6575, -30.864, 0.0 ], [ 150.6575, -30.886, 0.0 ] ] ] } },
{ "type": "Feature", "properties": { }, "geometry": { "type": "Polygon", "coordinates": [ [ [ 150.681, -30.886, 0.0 ], [ 150.7045, -30.886, 0.0 ], [ 150.7045, -30.864, 0.0 ], [ 150.681, -30.864, 0.0 ], [ 150.681, -30.886, 0.0 ] ] ] } },
{ "type": "Feature", "properties": { }, "geometry": { "type": "Polygon", "coordinates": [ [ [ 150.7045, -30.886, 0.0 ], [ 150.728, -30.886, 0.0 ], [ 150.728, -30.864, 0.0 ], [ 150.7045, -30.864, 0.0 ], [ 150.7045, -30.886, 0.0 ] ] ] } },
{ "type": "Feature", "properties": { }, "geometry": { "type": "Polygon", "coordinates": [ [ [ 150.728, -30.886, 0.0 ], [ 150.7515, -30.886, 0.0 ], [ 150.7515, -30.864, 0.0 ], [ 150.728, -30.864, 0.0 ], [ 150.728, -30.886, 0.0 ] ] ] } },
{ "type": "Feature", "properties": { }, "geometry": { "type": "Polygon", "coordinates": [ [ [ 150.7515, -30.886, 0.0 ], [ 150.775, -30.886, 0.0 ], [ 150.775, -30.864, 0.0 ], [ 150.7515, -30.864, 0.0 ], [ 150.7515, -30.886, 0.0 ] ] ] } },
{ "type": "Feature", "properties": { }, "geometry": { "type": "Polygon", "coordinates": [ [ [ 150.775, -30.886, 0.0 ], [ 150.7985, -30.886, 0.0 ], [ 150.7985, -30.864, 0.0 ], [ 150.775, -30.864, 0.0 ], [ 150.775, -30.886, 0.0 ] ] ] } },
{ "type": "Feature", "properties": { }, "geometry": { "type": "Polygon", "coordinates": [ [ [ 150.7985, -30.886, 0.0 ], [ 150.822, -30.886, 0.0 ], [ 150.822, -30.864, 0.0 ], [ 150.7985, -30.864, 0.0 ], [ 150.7985, -30.886, 0.0 ] ] ] } },
{ "type": "Feature", "properties": { }, "geometry": { "type": "Polygon", "coordinates": [ [ [ 150.822, -30.886, 0.0 ], [ 150.8455, -30.886, 0.0 ], [ 150.8455, -30.864, 0.0 ], [ 150.822, -30.864, 0.0 ], [ 150.822, -30.886, 0.0 ] ] ] } },
{ "type": "Feature", "properties": { }, "geometry": { "type": "Polygon", "coordinates": [ [ [ 150.8455, -30.886, 0.0 ], [ 150.869, -30.886, 0.0 ], [ 150.869, -30.864, 0.0 ], [ 150.8455, -30.864, 0.0 ], [ 150.8455, -30.886, 0.0 ] ] ] } },
{ "type": "Feature", "properties": { }, "geometry": { "type": "Polygon", "coordinates": [ [ [ 150.869, -30.886, 0.0 ], [ 150.8925, -30.886, 0.0 ], [ 150.8925, -30.864, 0.0 ], [ 150.869, -30.864, 0.0 ], [ 150.869, -30.886, 0.0 ] ] ] } },
{ "type": "Feature", "properties": { }, "geometry": { "type": "Polygon", "coordinates": [ [ [ 150.8925, -30.886, 0.0 ], [ 150.916, -30.886, 0.0 ], [ 150.916, -30.864, 0.0 ], [ 150.8925, -30.864, 0.0 ], [ 150.8925, -30.886, 0.0 ] ] ] } },
{ "type": "Feature", "properties": { }, "geometry": { "type": "Polygon", "coordinates": [ [ [ 150.916, -30.886, 0.0 ], [ 150.9395, -30.886, 0.0 ], [ 150.9395, -30.864, 0.0 ], [ 150.916, -30.864, 0.0 ], [ 150.916, -30.886, 0.0 ] ] ] } },
{ "type": "Feature", "properties": { }, "geometry": { "type": "Polygon", "coordinates": [ [ [ 150.9395, -30.886, 0.0 ], [ 150.963, -30.886, 0.0 ], [ 150.963, -30.864, 0.0 ], [ 150.9395, -30.864, 0.0 ], [ 150.9395, -30.886, 0.0 ] ] ] } },
{ "type": "Feature", "properties": { }, "geometry": { "type": "Polygon", "coordinates": [ [ [ 150.963, -30.886, 0.0 ], [ 150.9865, -30.886, 0.0 ], [ 150.9865, -30.864, 0.0 ], [ 150.963, -30.864, 0.0 ], [ 150.963, -30.886, 0.0 ] ] ] } },
{ "type": "Feature", "properties": { }, "geometry": { "type": "Polygon", "coordinates": [ [ [ 150.9865, -30.886, 0.0 ], [ 151.01, -30.886, 0.0 ], [ 151.01, -30.864, 0.0 ], [ 150.9865, -30.864, 0.0 ], [ 150.9865, -30.886, 0.0 ] ] ] } },
{ "type": "Feature", "properties": { }, "geometry": { "type": "Polygon", "coordinates": [ [ [ 150.54, -30.864, 0.0 ], [ 150.5635, -30.864, 0.0 ], [ 150.5635, -30.842, 0.0 ], [ 150.54, -30.842, 0.0 ], [ 150.54, -30.864, 0.0 ] ] ] } },
{ "type": "Feature", "properties": { }, "geometry": { "type": "Polygon", "coordinates": [ [ [ 150.5635, -30.864, 0.0 ], [ 150.587, -30.864, 0.0 ], [ 150.587, -30.842, 0.0 ], [ 150.5635, -30.842, 0.0 ], [ 150.5635, -30.864, 0.0 ] ] ] } },
{ "type": "Feature", "properties": { }, "geometry": { "type": "Polygon", "coordinates": [ [ [ 150.587, -30.864, 0.0 ], [ 150.6105, -30.864, 0.0 ], [ 150.6105, -30.842, 0.0 ], [ 150.587, -30.842, 0.0 ], [ 150.587, -30.864, 0.0 ] ] ] } },
{ "type": "Feature", "properties": { }, "geometry": { "type": "Polygon", "coordinates": [ [ [ 150.6105, -30.864, 0.0 ], [ 150.634, -30.864, 0.0 ], [ 150.634, -30.842, 0.0 ], [ 150.6105, -30.842, 0.0 ], [ 150.6105, -30.864, 0.0 ] ] ] } },
{ "type": "Feature", "properties": { }, "geometry": { "type": "Polygon", "coordinates": [ [ [ 150.634, -30.864, 0.0 ], [ 150.6575, -30.864, 0.0 ], [ 150.6575, -30.842, 0.0 ], [ 150.634, -30.842, 0.0 ], [ 150.634, -30.864, 0.0 ] ] ] } },
{ "type": "Feature", "properties": { }, "geometry": { "type": "Polygon", "coordinates": [ [ [ 150.6575, -30.864, 0.0 ], [ 150.681, -30.864, 0.0 ], [ 150.681, -30.842, 0.0 ], [ 150.6575, -30.842, 0.0 ], [ 150.6575, -30.864, 0.0 ] ] ] } },
{ "type": "Feature", "properties": { }, "geometry": { "type": "Polygon", "coordinates": [ [ [ 150.681, -30.864, 0.0 ], [ 150.7045, -30.864, 0.0 ], [ 150.7045, -30.842, 0.0 ], [ 150.681, -30.842, 0.0 ], [ 150.681, -30.864, 0.0 ] ] ] } },
{ "type": "Feature", "properties": { }, "geometry": { "type": "Polygon", "coordinates": [ [ [ 150.7045, -30.864, 0.0 ], [ 150.728, -30.864, 0.0 ], [ 150.728, -30.842, 0.0 ], [ 150.7045, -30.842, 0.0 ], [ 150.7045, -30.864, 0.0 ] ] ] } },
{ "type": "Feature", "properties": { }, "geometry": { "type": "Polygon", "coordinates": [ [ [ 150.728, -30.864, 0.0 ], [ 150.7515, -30.864, 0.0 ], [ 150.7515, -30.842, 0.0 ], [ 150.728, -30.842, 0.0 ], [ 150.728, -30.864, 0.0 ] ] ] } },
{ "type": "Feature", "properties": { }, "geometry": { "type": "Polygon", "coordinates": [ [ [ 150.7515, -30.864, 0.0 ], [ 150.775, -30.864, 0.0 ], [ 150.775, -30.842, 0.0 ], [ 150.7515, -30.842, 0.0 ], [ 150.7515, -30.864, 0.0 ] ] ] } },
{ "type": "Feature", "properties": { }, "geometry": { "type": "Polygon", "coordinates": [ [ [ 150.775, -30.864, 0.0 ], [ 150.7985, -30.864, 0.0 ], [ 150.7985, -30.842, 0.0 ], [ 150.775, -30.842, 0.0 ], [ 150.775, -30.864, 0.0 ] ] ] } },
{ "type": "Feature", "properties": { }, "geometry": { "type": "Polygon", "coordinates": [ [ [ 150.7985, -30.864, 0.0 ], [ 150.822, -30.864, 0.0 ], [ 150.822, -30.842, 0.0 ], [ 150.7985, -30.842, 0.0 ], [ 150.7985, -30.864, 0.0 ] ] ] } },
{ "type": "Feature", "properties": { }, "geometry": { "type": "Polygon", "coordinates": [ [ [ 150.822, -30.864, 0.0 ], [ 150.8455, -30.864, 0.0 ], [ 150.8455, -30.842, 0.0 ], [ 150.822, -30.842, 0.0 ], [ 150.822, -30.864, 0.0 ] ] ] } },
{ "type": "Feature", "properties": { }, "geometry": { "type": "Polygon", "coordinates": [ [ [ 150.8455, -30.864, 0.0 ], [ 150.869, -30.864, 0.0 ], [ 150.869, -30.842, 0.0 ], [ 150.8455, -30.842, 0.0 ], [ 150.8455, -30.864, 0.0 ] ] ] } },
{ "type": "Feature", "properties": { }, "geometry": { "type": "Polygon", "coordinates": [ [ [ 150.869, -30.864, 0.0 ], [ 150.8925, -30.864, 0.0 ], [ 150.8925, -30.842, 0.0 ], [ 150.869, -30.842, 0.0 ], [ 150.869, -30.864, 0.0 ] ] ] } },
{ "type": "Feature", "properties": { }, "geometry": { "type": "Polygon", "coordinates": [ [ [ 150.8925, -30.864, 0.0 ], [ 150.916, -30.864, 0.0 ], [ 150.916, -30.842, 0.0 ], [ 150.8925, -30.842, 0.0 ], [ 150.8925, -30.864, 0.0 ] ] ] } },
{ "type": "Feature", "properties": { }, "geometry": { "type": "Polygon", "coordinates": [ [ [ 150.916, -30.864, 0.0 ], [ 150.9395, -30.864, 0.0 ], [ 150.9395, -30.842, 0.0 ], [ 150.916, -30.842, 0.0 ], [ 150.916, -30.864, 0.0 ] ] ] } },
{ "type": "Feature", "properties": { }, "geometry": { "type": "Polygon", "coordinates": [ [ [ 150.9395, -30.864, 0.0 ], [ 150.963, -30.864, 0.0 ], [ 150.963, -30.842, 0.0 ], [ 150.9395, -30.842, 0.0 ], [ 150.9395, -30.864, 0.0 ] ] ] } },
{ "type": "Feature", "properties": { }, "geometry": { "type": "Polygon", "coordinates": [ [ [ 150.963, -30.864, 0.0 ], [ 150.9865, -30.864, 0.0 ], [ 150.9865, -30.842, 0.0 ], [ 150.963, -30.842, 0.0 ], [ 150.963, -30.864, 0.0 ] ] ] } },
{ "type": "Feature", "properties": { }, "geometry": { "type": "Polygon", "coordinates": [ [ [ 150.9865, -30.864, 0.0 ], [ 151.01, -30.864, 0.0 ], [ 151.01, -30.842, 0.0 ], [ 150.9865, -30.842, 0.0 ], [ 150.9865, -30.864, 0.0 ] ] ] } },
{ "type": "Feature", "properties": { }, "geometry": { "type": "Polygon", "coordinates": [ [ [ 150.54, -30.842, 0.0 ], [ 150.5635, -30.842, 0.0 ], [ 150.5635, -30.82, 0.0 ], [ 150.54, -30.82, 0.0 ], [ 150.54, -30.842, 0.0 ] ] ] } },
{ "type": "Feature", "properties": { }, "geometry": { "type": "Polygon", "coordinates": [ [ [ 150.5635, -30.842, 0.0 ], [ 150.587, -30.842, 0.0 ], [ 150.587, -30.82, 0.0 ], [ 150.5635, -30.82, 0.0 ], [ 150.5635, -30.842, 0.0 ] ] ] } },
{ "type": "Feature", "properties": { }, "geometry": { "type": "Polygon", "coordinates": [ [ [ 150.587, -30.842, 0.0 ], [ 150.6105, -30.842, 0.0 ], [ 150.6105, -30.82, 0.0 ], [ 150.587, -30.82, 0.0 ], [ 150.587, -30.842, 0.0 ] ] ] } },
{ "type": "Feature", "properties": { }, "geometry": { "type": "Polygon", "coordinates": [ [ [ 150.6105, -30.842, 0.0 ], [ 150.634, -30.842, 0.0 ], [ 150.634, -30.82, 0.0 ], [ 150.6105, -30.82, 0.0 ], [ 150.6105, -30.842, 0.0 ] ] ] } },
{ "type": "Feature", "properties": { }, "geometry": { "type": "Polygon", "coordinates": [ [ [ 150.634, -30.842, 0.0 ], [ 150.6575, -30.842, 0.0 ], [ 150.6575, -30.82, 0.0 ], [ 150.634, -30.82, 0.0 ], [ 150.634, -30.842, 0.0 ] ] ] } },
{ "type": "Feature", "properties": { }, "geometry": { "type": "Polygon", "coordinates": [ [ [ 150.6575, -30.842, 0.0 ], [ 150.681, -30.842, 0.0 ], [ 150.681, -30.82, 0.0 ], [ 150.6575, -30.82, 0.0 ], [ 150.6575, -30.842, 0.0 ] ] ] } },
{ "type": "Feature", "properties": { }, "geometry": { "type": "Polygon", "coordinates": [ [ [ 150.681, -30.842, 0.0 ], [ 150.7045, -30.842, 0.0 ], [ 150.7045, -30.82, 0.0 ], [ 150.681, -30.82, 0.0 ], [ 150.681, -30.842, 0.0 ] ] ] } },
{ "type": "Feature", "properties": { }, "geometry": { "type": "Polygon", "coordinates": [ [ [ 150.7045, -30.842, 0.0 ], [ 150.728, -30.842, 0.0 ], [ 150.728, -30.82, 0.0 ], [ 150.7045, -30.82, 0.0 ], [ 150.7045, -30.842, 0.0 ] ] ] } },
{ "type": "Feature", "properties": { }, "geometry": { "type": "Polygon", "coordinates": [ [ [ 150.728, -30.842, 0.0 ], [ 150.7515, -30.842, 0.0 ], [ 150.7515, -30.82, 0.0 ], [ 150.728, -30.82, 0.0 ], [ 150.728, -30.842, 0.0 ] ] ] } },
{ "type": "Feature", "properties": { }, "geometry": { "type": "Polygon", "coordinates": [ [ [ 150.7515, -30.842, 0.0 ], [ 150.775, -30.842, 0.0 ], [ 150.775, -30.82, 0.0 ], [ 150.7515, -30.82, 0.0 ], [ 150.7515, -30.842, 0.0 ] ] ] } },
{ "type": "Feature", "properties": { }, "geometry": { "type": "Polygon", "coordinates": [ [ [ 150.775, -30.842, 0.0 ], [ 150.7985, -30.842, 0.0 ], [ 150.7985, -30.82, 0.0 ], [ 150.775, -30.82, 0.0 ], [ 150.775, -30.842, 0.0 ] ] ] } },
{ "type": "Feature", "properties": { }, "geometry": { "type": "Polygon", "coordinates": [ [ [ 150.7985, -30.842, 0.0 ], [ 150.822, -30.842, 0.0 ], [ 150.822, -30.82, 0.0 ], [ 150.7985, -30.82, 0.0 ], [ 150.7985, -30.842, 0.0 ] ] ] } },
{ "type": "Feature", "properties": { }, "geometry": { "type": "Polygon", "coordinates": [ [ [ 150.822, -30.842, 0.0 ], [ 150.8455, -30.842, 0.0 ], [ 150.8455, -30.82, 0.0 ], [ 150.822, -30.82, 0.0 ], [ 150.822, -30.842, 0.0 ] ] ] } },
{ "type": "Feature", "properties": { }, "geometry": { "type": "Polygon", "coordinates": [ [ [ 150.8455, -30.842, 0.0 ], [ 150.869, -30.842, 0.0 ], [ 150.869, -30.82, 0.0 ], [ 150.8455, -30.82, 0.0 ], [ 150.8455, -30.842, 0.0 ] ] ] } },
{ "type": "Feature", "properties": { }, "geometry": { "type": "Polygon", "coordinates": [ [ [ 150.869, -30.842, 0.0 ], [ 150.8925, -30.842, 0.0 ], [ 150.8925, -30.82, 0.0 ], [ 150.869, -30.82, 0.0 ], [ 150.869, -30.842, 0.0 ] ] ] } },
{ "type": "Feature", "properties": { }, "geometry": { "type": "Polygon", "coordinates": [ [ [ 150.8925, -30.842, 0.0 ], [ 150.916, -30.842, 0.0 ], [ 150.916, -30.82, 0.0 ], [ 150.8925, -30.82, 0.0 ], [ 150.8925, -30.842, 0.0 ] ] ] } },
{ "type": "Feature", "properties": { }, "geometry": { "type": "Polygon", "coordinates": [ [ [ 150.916, -30.842, 0.0 ], [ 150.9395, -30.842, 0.0 ], [ 150.9395, -30.82, 0.0 ], [ 150.916, -30.82, 0.0 ], [ 150.916, -30.842, 0.0 ] ] ] } },
{ "type": "Feature", "properties": { }, "geometry": { "type": "Polygon", "coordinates": [ [ [ 150.9395, -30.842, 0.0 ], [ 150.963, -30.842, 0.0 ], [ 150.963, -30.82, 0.0 ], [ 150.9395, -30.82, 0.0 ], [ 150.9395, -30.842, 0.0 ] ] ] } },
{ "type": "Feature", "properties": { }, "geometry": { "type": "Polygon", "coordinates": [ [ [ 150.963, -30.842, 0.0 ], [ 150.9865, -30.842, 0.0 ], [ 150.9865, -30.82, 0.0 ], [ 150.963, -30.82, 0.0 ], [ 150.963, -30.842, 0.0 ] ] ] } },
{ "type": "Feature", "properties": { }, "geometry": { "type": "Polygon", "coordinates": [ [ [ 150.9865, -30.842, 0.0 ], [ 151.01, -30.842, 0.0 ], [ 151.01, -30.82, 0.0 ], [ 150.9865, -30.82, 0.0 ], [ 150.9865, -30.842, 0.0 ] ] ] } }
]
}
